vws_web_tools/__init__.py
vws_web_tools/py.typed
vws_web_tools-2024.10.6.1.dist-info/LICENSE
vws_web_tools-2024.10.6.1.dist-info/METADATA
vws_web_tools-2024.10.6.1.dist-info/WHEEL
vws_web_tools-2024.10.6.1.dist-info/entry_points.txt
vws_web_tools-2024.10.6.1.dist-info/top_level.txt
vws_web_tools-2024.10.6.1.dist-info/RECORD
