Metadata-Version: 2.1
Name: vws-web-tools
Version: 2024.10.6.1
Summary: Tools for interacting with the Vuforia Web Services (VWS) website.
Author-email: Adam Dangoor <adamdangoor@gmail.com>
License: MIT License
Project-URL: Source, https://github.com/VWS-Python/vws-web-tools
Keywords: vuforia,vws
Classifier: Development Status :: 5 - Production/Stable
Classifier: Environment :: Web Environment
Classifier: Framework :: Pytest
Classifier: License :: OSI Approved :: MIT License
Classifier: Operating System :: POSIX
Classifier: Programming Language :: Python :: 3 :: Only
Classifier: Programming Language :: Python :: 3.12
Requires-Python: >=3.12
License-File: LICENSE
Requires-Dist: beartype>=0.18.5
Requires-Dist: click
Requires-Dist: pyyaml
Requires-Dist: selenium
Provides-Extra: dev
Requires-Dist: actionlint-py==1.7.3.17; extra == "dev"
Requires-Dist: check-manifest==0.49; extra == "dev"
Requires-Dist: deptry==0.20.0; extra == "dev"
Requires-Dist: doc8==1.1.2; extra == "dev"
Requires-Dist: doccmd==2024.9.27; extra == "dev"
Requires-Dist: furo==2024.8.6; extra == "dev"
Requires-Dist: interrogate==1.7.0; extra == "dev"
Requires-Dist: mypy==1.11.2; extra == "dev"
Requires-Dist: pre-commit==3.8.0; extra == "dev"
Requires-Dist: pylint==3.3.1; extra == "dev"
Requires-Dist: pyproject-fmt==2.2.4; extra == "dev"
Requires-Dist: pyright==1.1.383; extra == "dev"
Requires-Dist: pyroma==4.2; extra == "dev"
Requires-Dist: pytest==8.3.3; extra == "dev"
Requires-Dist: pytest-cov==5.0.0; extra == "dev"
Requires-Dist: pytest-regressions==2.5.0; extra == "dev"
Requires-Dist: ruff==0.6.9; extra == "dev"
Requires-Dist: shellcheck-py==0.10.0.1; extra == "dev"
Requires-Dist: shfmt-py==3.7.0.1; extra == "dev"
Requires-Dist: sphinx==8.0.2; extra == "dev"
Requires-Dist: sphinx-click==6.0.0; extra == "dev"
Requires-Dist: sphinx-copybutton==0.5.2; extra == "dev"
Requires-Dist: sphinx-substitution-extensions==2024.8.6; extra == "dev"
Requires-Dist: sphinxcontrib-spelling==8; extra == "dev"
Requires-Dist: types-pyyaml==6.0.12.20240917; extra == "dev"
Requires-Dist: vulture==2.13; extra == "dev"
Provides-Extra: release
Requires-Dist: build; extra == "release"
Requires-Dist: check-wheel-contents; extra == "release"
